yarb.py
yarb_against_war-1.0.2.dist-info/METADATA
yarb_against_war-1.0.2.dist-info/WHEEL
yarb_against_war-1.0.2.dist-info/top_level.txt
yarb_against_war-1.0.2.dist-info/RECORD
