Metadata-Version: 2.1
Name: yarb-against-war
Version: 1.0.2
Summary: Yet Another Redis Backup utility
Author-email: Igor Vaiman <gosha.vaiman@gmail.com>
Project-URL: Homepage, https://github.com/bots-against-war/yarb
Requires-Dist: redis>=4.3.4
Requires-Dist: tqdm>=4.65.0
Requires-Dist: tenacity>=8.2.2
